utde/__init__.py
utde/checks.py
utde/errors.py
utde/lint.py
utde/persist.py
utde/profiling.py
utde-0.1.7.dist-info/METADATA
utde-0.1.7.dist-info/WHEEL
utde-0.1.7.dist-info/licenses/LICENSE
utde-0.1.7.dist-info/RECORD
