Metadata-Version: 2.3
Name: utde
Version: 0.1.7
Summary: A collection of python decorators I wish existed before
Author-email: Julian Goede <julian.goede@smartclip.tv>
License-File: LICENSE
Requires-Python: >=3.8
Requires-Dist: beartype>=0.18.5
Requires-Dist: ruff>=0.6.3
Provides-Extra: pandas
Requires-Dist: pandas>=2.2.2; extra == 'pandas'
